healthuniverse/__init__.py
healthuniverse/client.py
healthuniverse-0.1.2.dist-info/METADATA
healthuniverse-0.1.2.dist-info/WHEEL
healthuniverse-0.1.2.dist-info/RECORD
